hipersim/__init__.py
hipersim/_hipersim.py
hipersim/mann_turbulence.py
hipersim/version.py
hipersim/surrogates/AutoencoderModel_20Farms_10outputs.sav
hipersim/surrogates/PyWake_Surrogate_10Farms_Power_Autoencoder.sav
hipersim/surrogates/PyWake_Surrogate_10Farms_Power_RelativeLocation.sav
hipersim/surrogates/__init__.py
hipersim/surrogates/farm_utils.py
hipersim/surrogates/math_utils.py
hipersim/surrogates/neuralnets.py
hipersim/surrogates/os_utils.py
hipersim/turbgen/__init__.py
hipersim/turbgen/constrain_field.py
hipersim/turbgen/constrain_field_1d.py
hipersim/turbgen/generate_field.py
hipersim/turbgen/mannspectrum.py
hipersim/turbgen/manntensor.py
hipersim/turbgen/spectral_tensor.py
hipersim/turbgen/trapezoidal_sum_2d.py
hipersim/turbgen/turb_utils.py
hipersim/turbgen/turbgen.py
hipersim-0.1.13.dist-info/METADATA
hipersim-0.1.13.dist-info/WHEEL
hipersim-0.1.13.dist-info/top_level.txt
hipersim-0.1.13.dist-info/RECORD
