Metadata-Version: 2.4
Name: hipersim
Version: 0.1.13
Summary: A collection of wind energy simulation tools
Author-email: Nikolay Dimitrov <nkdi@dtu.dk>
Project-URL: Homepage, https://gitlab.windenergy.dtu.dk/HiperSim/hipersim
Classifier: Programming Language :: Python :: 3
Classifier: Operating System :: OS Independent
Classifier: License :: OSI Approved :: MIT License
Requires-Python: >=3.7
Requires-Dist: xarray
Requires-Dist: netcdf4
Requires-Dist: h5netcdf
Requires-Dist: scipy
Requires-Dist: tqdm
Requires-Dist: matplotlib
Provides-Extra: docs
Requires-Dist: sphinx; extra == "docs"
Requires-Dist: python-docs-theme; extra == "docs"
Requires-Dist: numpydoc; extra == "docs"
Requires-Dist: nbsphinx; extra == "docs"
Requires-Dist: sphinx_copybutton; extra == "docs"
Requires-Dist: sphinx_sitemap; extra == "docs"
Requires-Dist: ipympl; extra == "docs"
Requires-Dist: ipykernel; extra == "docs"
Provides-Extra: tests
Requires-Dist: wetb; extra == "tests"
Requires-Dist: h2lib; extra == "tests"
